ciomax/Conductor.ms
ciomax/Conductor.py
ciomax/VERSION
ciomax/__init__.py
ciomax/configuration_tab.py
ciomax/const.py
ciomax/post_install.py
ciomax/preview_tab.py
ciomax/render_scope.py
ciomax/response_tab.py
ciomax/store.py
ciomax/submit.py
ciomax/validation.py
ciomax/validation_tab.py
ciomax/components/__init__.py
ciomax/components/buttoned_scroll_panel.py
ciomax/components/checkbox_grp.py
ciomax/components/combo_box_grp.py
ciomax/components/combo_box_grp_2.py
ciomax/components/int_field_grp.py
ciomax/components/key_value_grp.py
ciomax/components/notice_grp.py
ciomax/components/software_combo_box_grp.py
ciomax/components/text_field_grp.py
ciomax/components/text_grp.py
ciomax/components/widgets.py
ciomax/icons/ConductorConnect_18x18.png
ciomax/icons/ConductorConnect_24x24.png
ciomax/icons/ConductorConnect_36x36.png
ciomax/icons/ConductorConnect_48x48.png
ciomax/icons/ConductorError_18x18.png
ciomax/icons/ConductorError_24x24.png
ciomax/icons/ConductorError_36x36.png
ciomax/icons/ConductorError_48x48.png
ciomax/icons/ConductorHelp_18x18.png
ciomax/icons/ConductorHelp_24x24.png
ciomax/icons/ConductorHelp_36x36.png
ciomax/icons/ConductorHelp_48x48.png
ciomax/icons/ConductorInfo_18x18.png
ciomax/icons/ConductorInfo_24x24.png
ciomax/icons/ConductorInfo_36x36.png
ciomax/icons/ConductorInfo_48x48.png
ciomax/icons/ConductorShow_18x18.png
ciomax/icons/ConductorShow_24x24.png
ciomax/icons/ConductorShow_36x36.png
ciomax/icons/ConductorShow_48x48.png
ciomax/icons/ConductorSubmit_18x18.png
ciomax/icons/ConductorSubmit_24x24.png
ciomax/icons/ConductorSubmit_36x36.png
ciomax/icons/ConductorSubmit_48x48.png
ciomax/icons/ConductorSuccess_18x18.png
ciomax/icons/ConductorSuccess_24x24.png
ciomax/icons/ConductorSuccess_36x36.png
ciomax/icons/ConductorSuccess_48x48.png
ciomax/icons/ConductorWarning_18x18.png
ciomax/icons/ConductorWarning_24x24.png
ciomax/icons/ConductorWarning_36x36.png
ciomax/icons/ConductorWarning_48x48.png
ciomax/icons/conductor_logo_white.png
ciomax-0.6.1.dist-info/METADATA
ciomax-0.6.1.dist-info/WHEEL
ciomax-0.6.1.dist-info/top_level.txt
ciomax-0.6.1.dist-info/RECORD
