Metadata-Version: 2.1
Name: ciomax
Version: 0.6.1
Summary: Max plugin for Conductor Cloud Rendering Platform.
Home-page: https://github.com/ConductorTechnologies/ciomax
Author: conductor
Author-email: info@conductortech.com
Classifier: Operating System :: OS Independent
Classifier: Programming Language :: Python
Classifier: Topic :: Multimedia :: Graphics :: 3D Rendering
Requires-Dist: ciocore <8.0.0,>=7.0.2
Requires-Dist: ciopath <2.0.0,>=1.1.2
Requires-Dist: cioseq <1.0.0,>=0.5.1
Requires-Dist: ciotemplate <1.0.0,>=0.1.2
